myLib/__init__.py
myLib/setup.py
myLib/datastructures/__init__.py
myLib/datastructures/setup.py
myLib/datastructures/linear/CDLL.py
myLib/datastructures/linear/CSLL.py
myLib/datastructures/linear/DLL.py
myLib/datastructures/linear/Queue.py
myLib/datastructures/linear/SLL.py
myLib/datastructures/linear/Stack.py
myLib/datastructures/linear/__init__.py
myLib/datastructures/nodes/DNode.py
myLib/datastructures/nodes/TNode.py
myLib/datastructures/nodes/__init__.py
myLib/datastructures/nodes/setup.py
myLib/datastructures/trees/AVL.py
myLib/datastructures/trees/BST.py
myLib/datastructures/trees/__init__.py
main_package_for_holding_dastructure_library-1.0.dist-info/METADATA
main_package_for_holding_dastructure_library-1.0.dist-info/WHEEL
main_package_for_holding_dastructure_library-1.0.dist-info/top_level.txt
main_package_for_holding_dastructure_library-1.0.dist-info/RECORD
