Metadata-Version: 2.1
Name: main-package-for-holding-dastructure-library
Version: 1.0
Summary: different types of datastructures
Author: Zachariah Blair
Author-email: zachariah.blair@gmail.com
